htmlcalendar.py
html_calendar-0.0.24.dist-info/WHEEL
html_calendar-0.0.24.dist-info/METADATA
html_calendar-0.0.24.dist-info/RECORD
