Metadata-Version: 2.1
Name: html-calendar
Version: 0.0.24
Summary: html-calendar
Author-email: Jorge Monforte Gonzalez <yo@llou.net>
Classifier: Development Status :: 3 - Alpha
Classifier: Environment :: Web Environment
Classifier: License :: OSI Approved :: BSD License
Classifier: Programming Language :: Python :: 3
Project-URL: Documentation, https://html-calendar.readthedocs.io/en/latest/
Project-URL: Home, https://github.com/llou/html-calendar
